PyCTD-0.5.7.dist-info/DESCRIPTION.rst
PyCTD-0.5.7.dist-info/METADATA
PyCTD-0.5.7.dist-info/RECORD
PyCTD-0.5.7.dist-info/WHEEL
PyCTD-0.5.7.dist-info/entry_points.txt
PyCTD-0.5.7.dist-info/metadata.json
PyCTD-0.5.7.dist-info/top_level.txt
pyctd/__init__.py
pyctd/cli.py
pyctd/constants.py
pyctd/manager/__init__.py
pyctd/manager/database.py
pyctd/manager/defaults.py
pyctd/manager/models.py
pyctd/manager/query.py
pyctd/manager/table.py
pyctd/manager/table_conf.py
pyctd/manager/model_types/__init__.py
pyctd/manager/model_types/action.py
pyctd/manager/model_types/model_types_old.py
