Metadata-Version: 2.0
Name: PyCTD
Version: 0.5.7
Summary: Importing and querying CTD
Home-page: https://github.com/cebel/pyctd
Author: Christian Ebeling
Author-email: christian.ebeling@scai.fraunhofer.de
License: Apache 2.0 License
Keywords: Toxicogenomics,Database,Bioinformatics,Human health
Platform: UNKNOWN
Classifier: Development Status :: 5 - Production/Stable
Classifier: Operating System :: OS Independent
Classifier: Environment :: Console
Classifier: Programming Language :: Python
Classifier: Programming Language :: Python :: 2.7
Classifier: Programming Language :: Python :: 3.4
Classifier: Programming Language :: Python :: 3.5
Classifier: Programming Language :: Python :: 3.6
Classifier: Intended Audience :: Developers
Classifier: License :: OSI Approved :: MIT License
Classifier: Topic :: Database
Classifier: Topic :: Scientific/Engineering :: Bio-Informatics
Requires-Dist: click
Requires-Dist: pandas
Requires-Dist: pymysql
Requires-Dist: requests
Requires-Dist: sqlalchemy
